Metadata-Version: 1.0
Name: terminal-colorizer
Version: 0.23
Summary: Colors your terminal
Home-page: UNKNOWN
Author: UNKNOWN
Author-email: xcensed@gmail.com
License: UNKNOWN
Platform: UNKNOWN
